{
  "project_info": {
    "project_number": "881481109931",
    "project_id": "navermapex-2",
    "storage_bucket": "navermapex-2.appspot.com"
  },
  "client": [
    {
      "client_info": {
        "mobilesdk_app_id": "1:881481109931:android:447365a1f1c616fd5082ee",
        "android_client_info": {
          "package_name": "com.example.navermapex_2"
        }
      },
      "oauth_client": [
        {
          "client_id": "881481109931-ro82igdqean5br8qagkk4qva38orporm.apps.googleusercontent.com",
          "client_type": 3
        }
      ],
      "api_key": [
        {
          "current_key": "AIzaSyAyf5CJAhGvUbYwyAe0ygM-cznUHuOBayI"
        }
      ],
      "services": {
        "appinvite_service": {
          "other_platform_oauth_client": [
            {
              "client_id": "881481109931-ro82igdqean5br8qagkk4qva38orporm.apps.googleusercontent.com",
              "client_type": 3
            }
          ]
        }
      }
    }
  ],
  "configuration_version": "1"
}